README.md
setup.py
lo4container/__init__.py
lo4container.egg-info/PKG-INFO
lo4container.egg-info/SOURCES.txt
lo4container.egg-info/dependency_links.txt
lo4container.egg-info/not-zip-safe
lo4container.egg-info/top_level.txt