Metadata-Version: 2.1
Name: lo4container
Version: 0.1.6
Summary: The simplest IoC in python
Home-page: https://gitlab.com/lo4p/lo4container
Author: Phuong Huynh
Author-email: lo4kings@gmail.com
License: MIT
Platform: UNKNOWN
